[
  {
    "page_number": 0,
    "bbox": [
      72.02,
      137.08,
      400.69,
      267.79
    ],
    "text": "01. - .",
    "fonts": [
      "IskoolaPota-Bold"
    ],
    "sizes": [
      6.960000038146973,
      9.960000038146973,
      14.039999961853027
    ]
  },
  {
    "page_number": 0,
    "bbox": [
      72.02,
      267.74,
      526.94,
      323.35
    ],
    "text": "2025.09.17 .",
    "fonts": [
      "IskoolaPota"
    ],
    "sizes": [
      6.960000038146973,
      14.039999961853027
    ]
  },
  {
    "page_number": 0,
    "bbox": [
      72.02,
      323.71,
      501.16,
      347.83
    ],
    "text": "45 .",
    "fonts": [
      "IskoolaPota",
      "IskoolaPota-Bold"
    ],
    "sizes": [
      6.960000038146973,
      14.039999961853027
    ]
  },
  {
    "page_number": 0,
    "bbox": [
      72.02,
      347.78,
      527.07,
      492.45
    ],
    "text": ". 24 . 02. - .",
    "fonts": [
      "IskoolaPota",
      "IskoolaPota-Bold"
    ],
    "sizes": [
      6.960000038146973,
      14.039999961853027
    ]
  },
  {
    "page_number": 0,
    "bbox": [
      72.02,
      492.4,
      526.93,
      629.9
    ],
    "text": "2025.09.17 , 59416 , , 12390 , 96986 , 104360 105268 .",
    "fonts": [
      "IskoolaPota"
    ],
    "sizes": [
      9.0,
      14.039999961853027
    ]
  },
  {
    "page_number": 0,
    "bbox": [
      72.02,
      630.24,
      527.07,
      721.85
    ],
    "text": "28 .",
    "fonts": [
      "IskoolaPota",
      "IskoolaPota-Bold"
    ],
    "sizes": [
      9.0,
      14.039999961853027
    ]
  },
  {
    "page_number": 0,
    "bbox": [
      68.42,
      132.76,
      397.5,
      153.18
    ],
    "text": "D/Media/Out/1764/2025 2025.09.18 0630",
    "fonts": [
      "Calibri",
      "IskoolaPota"
    ],
    "sizes": [
      9.0
    ]
  },
  {
    "page_number": 1,
    "bbox": [
      72.02,
      36.38,
      527.01,
      77.3
    ],
    "text": "03. - .",
    "fonts": [
      "IskoolaPota-Bold"
    ],
    "sizes": [
      6.960000038146973,
      14.039999961853027
    ]
  },
  {
    "page_number": 1,
    "bbox": [
      72.02,
      77.27,
      526.94,
      220.41
    ],
    "text": "2025.09.17 84523 , 31906 , 91459 , 96927 , 25779 102438 .",
    "fonts": [
      "IskoolaPota"
    ],
    "sizes": [
      14.039999961853027
    ]
  },
  {
    "page_number": 1,
    "bbox": [
      72.02,
      220.72,
      527.08,
      296.13
    ],
    "text": "16 , . 04. - .",
    "fonts": [
      "IskoolaPota",
      "IskoolaPota-Bold"
    ],
    "sizes": [
      9.0,
      14.039999961853027
    ]
  },
  {
    "page_number": 1,
    "bbox": [
      72.02,
      296.06,
      526.91,
      383.47
    ],
    "text": "2025.09.18 19 . .",
    "fonts": [
      "IskoolaPota"
    ],
    "sizes": [
      6.960000038146973,
      14.039999961853027
    ]
  },
  {
    "page_number": 1,
    "bbox": [
      72.02,
      383.83,
      526.93,
      488.66
    ],
    "text": "34 . . .",
    "fonts": [
      "IskoolaPota",
      "IskoolaPota-Bold"
    ],
    "sizes": [
      6.960000038146973,
      14.039999961853027
    ]
  },
  {
    "page_number": 1,
    "bbox": [
      107.42,
      491.49,
      257.75,
      507.74
    ],
    "text": ".",
    "fonts": [
      "IskoolaPota-Bold"
    ],
    "sizes": [
      14.039999961853027
    ]
  }
]