[
  {
    "page_number": 0,
    "bbox": [
      72.02,
      202.04,
      411.61,
      260.17
    ],
    "text": "\u0db4 \u0ddc\u0dbd\u0dd2\u0dc3\u0dca \u0db8\u0ddc\u0db0\u0dca\u200d\u0dba \u0db4 \u0ddc\u0da7\u0dca\u0da8\u0ddc\u0dc3\u0dba \u0db4\u0dd9\u0dad \u0dd9\u0ddc\u0dbb\u0dca\u0dad\u0ddc \u0dc0\u0dd6 \u0dd9\u0dd0\u0daf\u0d9c\u0dad\u0dca \u0db4\u0dad\u0ddc\u0dbb\u0dad\u0dd4\u0dbb\u0dd4. \u0baa\u0baa\u0bca\u0bb2\u0bbf\u0bb8\u0bcd \u0b8a\u0b9f\u0b95\u0baa\u0bcd \u0baa\u0bbf\u0bca\u0bbf\u0bb5\u0bbf\u0bb1\u0bcd\u0b95\u0bc1 \u0b85\u0bb1\u0bbf\u0bb5\u0bbf\u0b95\u0bcd\u0b95\u0baa\u0bcd\u0baa\u0b9f\u0bcd\u0b9f \u0bae\u0bc1\u0b95\u0bcd\u0b95\u0bbf\u0baf \u0ba4\u0b95\u0bb5\u0bb2\u0bcd\u0b95\u0bb3\u0bcd",
    "fonts": [
      "IskoolaPota-Bold",
      "Kavivanar-Regular"
    ],
    "sizes": [
      9.0,
      9.960000038146973,
      12.0,
      14.039999961853027
    ]
  },
  {
    "page_number": 0,
    "bbox": [
      72.02,
      262.6,
      376.96,
      321.92
    ],
    "text": "Important Information Reported to the Police Media Division 01. \u0db8\u0db1\u0dd4\u0dc2\u0dca\u200d\u0dba \u0d9d\u0ddc\u0dad\u0db1\u0dba\u0d9a\u0dca - \u0dd9\u0db1\u0ddc\u0dad\u0dc0\u0dd2\u0dbd\u0dca\u0dbd\u0dd4\u0dd9 \u0db4 \u0ddc\u0dbd\u0dd2\u0dc3\u0dca \u0dd9\u0dc3\u0db8.",
    "fonts": [
      "IskoolaPota-Bold",
      "Latha,Bold",
      "TimesNewRomanPSMT"
    ],
    "sizes": [
      6.960000038146973,
      12.0,
      14.039999961853027
    ]
  },
  {
    "page_number": 0,
    "bbox": [
      72.02,
      319.94,
      526.93,
      395.12
    ],
    "text": "2026.06.09 \u0dc0\u0db1 \u0daf\u0dd2\u0db1 \u0d85\u0dc5\u0dd4\u0dba\u0db8\u0dca \u0d9a\u0dcf\u0dbd\u0dba\u0dda \u0dc0\u0db1\u0dcf\u0dad\u0dc0\u0dd2\u0dbd\u0dca\u0dbd\u0dd4\u0dc0 \u0dba \u0dcf\u0dbd\u0dd2\u0dc3\u0dca \u0dc0\u0dc3\u0dba\u0db8\u0dca \u0d9a\u0dbb\u0dad\u0dd2\u0dc0\u0dca \u0db4\u0dca\u200d\u0dbb\u0dba\u0dda\u0dc1\u0dba\u0dda \u0d9a\u0da2\u0dd4 \u0dc0\u0dad\u0dca\u0dad\u0d9a\u0dca \u0dad\u0dd4\u0dbd\u0daf\u0dd3 \u0db4\u0dd4\u0dda\u0d9c\u0dbd\u0dba\u0dba\u0d9a\u0dd4\u0da7 \u0dc4\u0dbb\u0daf\u0dd3 \u0dba\u0dc0\u0da9\u0dd2\u0dad\u0db6\u0dcf \u0d9d\u0dcf\u0dad\u0db1\u0dba \u0d9a\u0dbb \u0d87\u0dad\u0dd2 \u0db6\u0dc0\u0da7 \u0dc0\u0db1\u0dcf\u0dad\u0dc0\u0dd2\u0dbd\u0dca\u0dbd\u0dd4\u0dc0 \u0dba \u0dcf\u0dbd\u0dd2\u0dc3\u0dca \u0dc3\u0dca\u0dae\u0dcf\u0db1\u0dba \u0dba\u0dc0\u0dad \u0dbd\u0daf \u0dab\u0dd2\u0dc0\u0dd2\u0da9\u0dba\u0d9a\u0dca \u0db8\u0dad \u0dc0\u0dd2\u0db8\u0dbb\u0dca\u0dc1\u0db1 \u0d86\u0dbb\u0db8\u0dca\u0db7 \u0d9a\u0dbb \u0d87\u0dad.",
    "fonts": [
      "IskoolaPota",
      "Latha",
      "Latha,Bold"
    ],
    "sizes": [
      6.960000038146973,
      14.039999961853027
    ]
  },
  {
    "page_number": 0,
    "bbox": [
      108.02,
      392.33,
      527.07,
      624.37
    ],
    "text": "\u0db8\u0dbb\u0dab \u0dbb\u0dd4 \u0dd9\u0dba\u0dc3 \u0d85\u0dc0\u0dd4\u0dbb\u0dd4\u0daf\u0dd4 34 \u0d9a\u0dca \u0dc0\u0dd6 \u0dbd\u0dca\u0dbd\u0d85\u0da9\u0dd2\u0dba \u0db4\u0dca\u200d\u0dbb\u0db4\u0dda\u0dc1\u0db4\u0dda \u0daf\u0dd2\u0d82\u0da0\u0dd2 \u0dbb\u0dd4\u0db4\u0dd9\u0d9a\u0dd2. \u0db8\u0dbb\u0dab\u0d9a\u0dbb\u0dd4 \u0d9a\u0dbb\u0dad\u0dd2\u0dc0\u0dca \u0db4\u0dd2\u0dc4\u0dd2\u0da7\u0dd2 \u0dc0\u0dd0\u0dc0\u0dd2\u0dbd\u0dd2 \u0dc3\u0db8\u0dcf\u0d9c\u0db8\u0d9a\u0da7 \u0d85\u0dba\u0dad\u0dca \u0d9a\u0da2\u0dd4 \u0dc0\u0dad\u0dca\u0dad\u0d9a \u0d9a\u0da2\u0dd4 \u0d87\u0dc4\u0dd2\u0daf\u0dd3\u0db8\u0da7 \u0dba\u0d9c\u0dcf\u0dc3\u0dca \u0dc3\u0dd2\u0da7\u0dd2\u0dba\u0daf\u0dd3 \u0d91\u0dc4\u0dd2 \u0db8\u0dd4\u0dbb\u0d9a\u0dbb\u0dd4\u0dc0\u0db1\u0dca\u0da7 \u0dc4\u0dc3\u0dd4\u0dc0\u0dd3 \u0d94\u0dc0\u0dd4\u0db1\u0dca \u0dc0\u0dd2\u0dc3\u0dd2\u0db1\u0dca \u0dc4\u0dbb\u0daf\u0dd3 \u0dc0\u0dcf\u0dba\u0dd4 \u0dbb\u0dba\u0dd2\u0dc6\u0dbd\u0dca\u0dbd \u0d85\u0dc0\u0dd2\u0dba\u0d9a\u0dd2\u0db1\u0dca \u0db6\u0dc0\u0da7 \u0dc3\u0dd0\u0d9a \u0dba\u0d9a\u0dba\u0dbb\u0db1 \u0d85\u0dc0\u0dd2\u0dba\u0d9a\u0dd2\u0db1\u0dca \u0dba\u0dc0\u0da9\u0dd2 \u0dad\u0db6\u0dcf \u0dba\u0db8\u0db8 \u0d9d\u0dcf\u0dad\u0db1\u0dba \u0dc3\u0dd2\u0daf\u0dd4\u0d9a\u0dbb \u0d87\u0dad\u0dd2 \u0db6\u0dc0\u0da7 \u0daf\u0dd0\u0db1\u0da7 \u0dc3\u0dd2\u0daf\u0dd4 \u0d9a\u0dbb\u0db1 \u0dbd\u0daf \u0dc0\u0dd2\u0db8\u0dbb\u0dca\u0dc1\u0db1\u0dba\u0dda\u0daf\u0dd3 \u0d85\u0db1\u0dcf\u0dc0\u0dbb\u0dab\u0dba \u0dc0\u0dd3 \u0d87\u0dad. \u0dc3\u0dd2\u0dda\u0dd2\u0dba \u0dc3\u0db8\u0dca\u0db6\u0db1\u0dca\u0db0\u0dca\u200d\u0db4\u0dba\u0db1\u0dca \u0d91\u0db8 \u0dd9\u0dad\u0dd4\u0dba\u0ddc\u0db4\u0dda \u0db8\u0dd4\u0dbb \u0dbb\u0dd4\u0dd9\u0db1\u0dca 08 \u0db4\u0daf\u0db4\u0db1\u0d9a\u0dd4 \u0dd9\u0ddc\u0dba\u0dd4 \u0dbb\u0dba\u0dd2\u0dc6\u0dbd\u0dca\u0dbd \u0d85\u0dc0\u0dd2 04 \u0d9a\u0dca \u0daf \u0dc3\u0db8\u0d9f \u0d85\u0dad\u0dca\u0d85\u0da9\u0dd2\u0d82\u0d9c\u0dd4\u0dd9\u0da7 \u0db4\u0d9c\u0db1 \u0d87\u0dad. \u0dc3\u0dd0 \u0dbb\u0dd4\u0dd9\u0db1\u0dca \u0d85\u0dc0\u0dd4\u0dbb\u0dd4\u0daf\u0dd4 19 \u0dad\u0dca 41 \u0dad\u0dca \u0d85\u0dad\u0dbb \u0dd9\u0dba\u0dc3\u0dca\u0dd9\u0dbd \u0dc3\u0dd4\u0dd9\u0db1 \u0d92\u0dad\u0dca\u0dad\u0ddc\u0db4\u0dbd\u0dca\u0dbd, \u0db4\u0dd4\u0dad\u0dca\u0dad\u0dbd\u0db8, \u0dbd\u0dca\u0dbd\u0dd2\u0da7\u0dd2\u0dba, \u0d85\u0db1\u0dd4\u0dbb\u0ddc\u0db0\u0dca\u200d\u0db4\u0dd4\u0dbb \u0db4\u0dca\u200d\u0dbb\u0db4\u0dda\u0dc1\u0dd9\u0dbd \u0daf\u0dd2\u0d82\u0da0\u0dd2 \u0dbb\u0dd4\u0dd9\u0db1\u0dca \u0db4\u0dda. \u0db8\u0dd8\u0dad \u0dc1\u0dbb\u0dd3\u0dbb\u0dba \u0dc1\u0dca\u0da0\u0dcf\u0dad\u0dca \u0db8\u0dbb\u0dab \u0dbb\u0dd3\u0d9a\u0dca\u0dc2\u0dab\u0dba \u0dc3\u0db3\u0dc4\u0dcf \u0db4\u0dd4\u0dad\u0dca\u0dad\u0dbd\u0db8 \u0dba\u0dbb\u0ddd\u0dc4\u0dba\u0dbd\u0dca\u0dbd \u0db8\u0dd8\u0dad \u0dc1\u0dbb\u0dd3\u0dbb\u0dcf\u0d9c\u0dcf\u0dbb\u0dba\u0dda \u0dad\u0dd0\u0db1\u0dca \u0dad\u0dca \u0d9a\u0dbb \u0d87\u0dad\u0dd2 \u0d85\u0dad\u0dbb \u0dc0\u0db1\u0dcf\u0dad\u0dc0\u0dd2\u0dbd\u0dca\u0dbd\u0dd4\u0dc0 \u0dba \u0dcf\u0dbd\u0dd2\u0dc3\u0dd2\u0dba \u0dc0\u0dd0\u0da9\u0dd2\u0daf\u0dd4\u0dbb \u0dc0\u0dd2\u0db8\u0dbb\u0dca\u0dc1\u0db1 \u0dc3\u0dd2\u0daf\u0dd4 \u0d9a\u0dbb\u0db1\u0dd4 \u0dbd\u0db6\u0dba\u0dd2.",
    "fonts": [
      "Calibri",
      "IskoolaPota",
      "IskoolaPota-Bold",
      "Latha",
      "Latha,Bold"
    ],
    "sizes": [
      6.960000038146973,
      9.960000038146973,
      14.039999961853027
    ]
  },
  {
    "page_number": 0,
    "bbox": [
      108.02,
      632.44,
      390.54,
      650.34
    ],
    "text": "\u0baa\u0b95\u0bca\u0bb2\u0bb2\u0b9a\u0bcd \u0b9a\u0bae\u0bcd\u0baa\u0bb5\u0bae\u0bcd \u2013 \u0bb5\u0ba9\u0bca\u0ba4\u0bcd\u0ba4\u0bb5\u0bbf\u0bb2\u0bcd\u0bb2\u0bc1\u0bb5 \u0baa\u0baa\u0bca\u0bb2\u0bbf\u0bb8\u0bcd \u0baa\u0bbf\u0bca\u0bbf\u0bb5\u0bc1",
    "fonts": [
      "Kavivanar-Regular"
    ],
    "sizes": [
      12.0
    ]
  },
  {
    "page_number": 0,
    "bbox": [
      108.02,
      664.24,
      525.81,
      735.42
    ],
    "text": "2026.06.09 \u0b85\u0ba9\u0bcd\u0bb1\u0bc1 \u0b85\u0ba4\u0bbf\u0b95\u0bca\u0bb2\u0bb2, \u0bb5\u0ba9\u0bca\u0ba4\u0bcd\u0ba4\u0bb5\u0bbf\u0bb2\u0bcd\u0bb2\u0bc1\u0bb5 \u0baa\u0baa\u0bca\u0bb2\u0bbf\u0bb8\u0bcd \u0baa\u0bbf\u0bca\u0bbf\u0bb5\u0bbf\u0bb1\u0bcd\u0b95\u0bc1\u0b9f\u0bcd\u0baa\u0b9f\u0bcd\u0b9f \u0b95\u0bb0\u0ba4\u0bc0\u0bb5\u0bc1 \u0baa\u0b95\u0bc1\u0ba4\u0bbf\u0baf\u0bbf\u0bb2\u0bcd \u0b89\u0bb3\u0bcd\u0bb3 \u0bae\u0bc1\u0ba8\u0bcd\u0ba4\u0bbf\u0bca\u0bbf\u0ba4\u0bcd \u0ba4\u0ba4\u0bca\u0b9f\u0bcd\u0b9f\u0ba4\u0bcd\u0ba4\u0bbf\u0bb2\u0bcd \u0b92\u0bb0\u0bc1\u0bb5\u0bca\u0bcd \u0ba4\u0bca\u0b95\u0bcd\u0b95\u0baa\u0bcd\u0baa\u0b9f\u0bcd\u0b9f\u0bc1 \u0ba4\u0bc1\u0baa\u0bcd\u0baa\u0bca\u0b95\u0bcd\u0b95\u0bbf\u0b9a\u0bcd \u0b9a\u0bc2\u0b9f\u0bcd\u0b9f\u0bbf\u0bb2\u0bcd \u0baa\u0b95\u0bca\u0bb2\u0bb2 \u0baa\u0b9a\u0baf\u0bcd\u0baf\u0baa\u0bcd\u0baa\u0b9f\u0bcd\u0b9f\u0ba4\u0bca\u0b95 \u0b95\u0bbf\u0bb2\u0b9f\u0ba4\u0bcd\u0ba4 \u0ba4\u0b95\u0bb5\u0bb2\u0bbf\u0ba9\u0bcd \u0b85\u0b9f\u0bbf\u0baa\u0bcd\u0baa\u0bb2\u0b9f\u0baf\u0bbf\u0bb2\u0bcd \u0bb5\u0bbf\u0b9a\u0bca\u0bb0\u0bb2\u0bc8\u0b95\u0bb3\u0bcd \u0b86\u0bb0\u0bae\u0bcd\u0baa\u0bbf\u0b95\u0bcd\u0b95\u0baa\u0bcd\u0baa\u0b9f\u0bcd\u0b9f\u0bc1\u0bb3\u0bcd\u0bb3\u0ba9.",
    "fonts": [
      "Kavivanar-Regular"
    ],
    "sizes": [
      12.0
    ]
  },
  {
    "page_number": 0,
    "bbox": [
      108.02,
      749.46,
      469.65,
      767.24
    ],
    "text": "\u0b89\u0baf\u0bbf\u0bca\u0bbf\u0bb4\u0ba8\u0bcd\u0ba4\u0bb5\u0bca\u0bcd 34 \u0bb5\u0baf\u0ba4\u0bc1\u0bb2\u0b9f\u0baf \u0b95\u0bb2\u0bcd\u0b85\u0b9f\u0bbf\u0baf \u0baa\u0b95\u0bc1\u0ba4\u0bbf\u0bb2\u0baf\u0b9a\u0bcd \u0ba4\u0b9a\u0bca\u0bcd\u0ba8\u0bcd\u0ba4\u0bb5\u0bca\u0bcd \u0b86\u0bb5\u0bca\u0bca\u0bcd.",
    "fonts": [
      "Kavivanar-Regular"
    ],
    "sizes": [
      12.0
    ]
  },
  {
    "page_number": 0,
    "bbox": [
      64.94,
      161.44,
      390.9,
      181.86
    ],
    "text": "D/Media/Out/ 936 /2026 2026.06.10 \u0dd0\u0dba 0530",
    "fonts": [
      "Calibri",
      "IskoolaPota"
    ],
    "sizes": [
      9.0
    ]
  },
  {
    "page_number": 1,
    "bbox": [
      108.02,
      31.5,
      525.93,
      120.46
    ],
    "text": "\u0b95\u0bb0\u0ba4\u0bc0\u0bb5\u0bc1 \u0baa\u0b95\u0bc1\u0ba4\u0bbf\u0baf\u0bbf\u0bb2\u0bcd \u0b89\u0bb3\u0bcd\u0bb3 \u0b92\u0bb0\u0bc1 \u0ba4\u0ba4\u0bca\u0b9f\u0bcd\u0b9f \u0ba8\u0bbf\u0bb1\u0bc1\u0bb5\u0ba9\u0ba4\u0bcd\u0ba4\u0bbf\u0bb1\u0bcd\u0b95\u0bc1\u0b9a\u0bcd \u0baa\u0b9a\u0bca\u0ba8\u0bcd\u0ba4\u0bae\u0bca\u0ba9 \u0bae\u0bc1\u0ba8\u0bcd\u0ba4\u0bbf\u0bca\u0bbf\u0ba4\u0bcd \u0ba4\u0ba4\u0bca\u0b9f\u0bcd\u0b9f\u0ba4\u0bcd\u0ba4\u0bbf\u0bb2\u0bcd \u0bae\u0bc1\u0ba8\u0bcd\u0ba4\u0bbf\u0bca\u0bbf \u0ba4\u0b9a\u0b95\u0bca\u0bbf\u0b95\u0bcd\u0b95\u0b9a\u0bcd \u0baa\u0b9a\u0ba9\u0bcd\u0bb1\u0ba4\u0baa\u0bca\u0ba4\u0bc1, \u0b85\u0b99\u0bcd\u0b95\u0bc1\u0bb3\u0bcd\u0bb3 \u0b95\u0bca\u0bb5\u0bb2\u0bca\u0bcd\u0b95\u0bb3\u0bca\u0bb2\u0bcd \u0baa\u0bbf\u0b9f\u0bbf\u0b95\u0bcd\u0b95\u0baa\u0bcd\u0baa\u0b9f\u0bcd\u0b9f\u0bc1 \u0ba4\u0bca\u0b95\u0bcd\u0b95\u0baa\u0bcd\u0baa\u0b9f\u0bcd\u0b9f\u0ba4\u0bc1\u0b9f\u0ba9\u0bcd, \u0b95\u0bca\u0bb1\u0bcd\u0bb1\u0bc1\u0ba4\u0bcd \u0ba4\u0bc1\u0baa\u0bcd\u0baa\u0bca\u0b95\u0bcd\u0b95\u0bbf (Air Rifle) \u0b8e\u0ba9 \u0b9a\u0ba8\u0bcd\u0ba4\u0ba4\u0b95\u0bbf\u0b95\u0bcd\u0b95\u0baa\u0bcd\u0baa\u0b9f\u0bc1\u0bae\u0bcd \u0b86\u0baf\u0bc1\u0ba4\u0ba4\u0bcd\u0ba4\u0bca\u0bb2\u0bcd \u0b9a\u0bc1\u0b9f\u0bcd\u0b9f\u0bc1\u0b95\u0bcd \u0baa\u0b95\u0bca\u0bb2\u0bcd\u0bb2\u0baa\u0bcd\u0baa\u0b9f\u0bcd\u0b9f\u0ba4\u0bca\u0b95 \u0b86\u0bb0\u0bae\u0bcd\u0baa\u0b95\u0b9f\u0bcd\u0b9f \u0bb5\u0bbf\u0b9a\u0bca\u0bb0\u0bb2\u0bc8\u0b95\u0bb3\u0bbf\u0bb2\u0bcd \u0baa\u0ba4\u0bca\u0bbf\u0baf\u0bb5\u0ba8\u0bcd\u0ba4\u0bc1\u0bb3\u0bcd\u0bb3\u0ba4\u0bc1.",
    "fonts": [
      "Kavivanar-Regular"
    ],
    "sizes": [
      12.0
    ]
  },
  {
    "page_number": 1,
    "bbox": [
      108.02,
      134.36,
      525.92,
      205.66
    ],
    "text": "\u0b87\u0b9a\u0bcd \u0b9a\u0bae\u0bcd\u0baa\u0bb5\u0bae\u0bcd \u0baa\u0ba4\u0bca\u0b9f\u0bca\u0bcd\u0baa\u0bca\u0b95 \u0ba4\u0ba4\u0bca\u0b9f\u0bcd\u0b9f\u0ba4\u0bcd\u0ba4\u0bbf\u0ba9\u0bcd 08 \u0b95\u0bca\u0bb5\u0bb2\u0bca\u0bcd\u0b95\u0bb3\u0bcd \u0bae\u0bb1\u0bcd\u0bb1\u0bc1\u0bae\u0bcd 04 \u0b95\u0bca\u0bb1\u0bcd\u0bb1\u0bc1\u0ba4\u0bcd \u0ba4\u0bc1\u0baa\u0bcd\u0baa\u0bca\u0b95\u0bcd\u0b95\u0bbf\u0b95\u0bb3\u0bcd \u0bb2\u0b95\u0baa\u0bcd\u0baa\u0bb1\u0bcd\u0bb1\u0baa\u0bcd\u0baa\u0b9f\u0bcd\u0b9f\u0bc1\u0bb3\u0bcd\u0bb3\u0ba9. \u0b9a\u0ba8\u0bcd\u0ba4\u0ba4\u0b95\u0ba8\u0baa\u0bca\u0bcd\u0b95\u0bb3\u0bcd 19 \u0bae\u0bc1\u0ba4\u0bb2\u0bcd 41 \u0bb5\u0baf\u0ba4\u0bc1\u0b95\u0bcd\u0b95\u0bc1\u0b9f\u0bcd\u0baa\u0b9f\u0bcd\u0b9f\u0bb5\u0bca\u0bcd\u0b95\u0bb3\u0bca\u0b95\u0bb5\u0bc1\u0bae\u0bcd, \u0b8f\u0ba4\u0bcd\u0ba4\u0bca\u0ba4\u0bb2, \u0baa\u0bc1\u0ba4\u0bcd\u0ba4\u0bb3\u0bae\u0bcd, \u0b95\u0bb2\u0bcd\u0baa\u0bbf\u0b9f\u0bcd\u0b9f\u0bbf \u0bae\u0bb1\u0bcd\u0bb1\u0bc1\u0bae\u0bcd \u0b85\u0ba9\u0bc1\u0bb0\u0bca\u0ba4\u0baa\u0bc1\u0bb0\u0bae\u0bcd \u0baa\u0b95\u0bc1\u0ba4\u0bbf\u0b95\u0bb2\u0bb3\u0b9a\u0bcd \u0ba4\u0b9a\u0bca\u0bcd\u0ba8\u0bcd\u0ba4\u0bb5\u0bca\u0bcd\u0b95\u0bb3\u0bca\u0b95\u0bb5\u0bc1\u0bae\u0bcd \u0b89\u0bb3\u0bcd\u0bb3\u0ba9\u0bca\u0bcd.",
    "fonts": [
      "Kavivanar-Regular"
    ],
    "sizes": [
      12.0
    ]
  },
  {
    "page_number": 1,
    "bbox": [
      108.02,
      219.56,
      525.76,
      273.01
    ],
    "text": "\u0b9a\u0b9f\u0bb2\u0bae\u0bcd \u0baa\u0bca\u0bbf\u0ba4\u0b9a\u0bca\u0ba4\u0bb2\u0ba9\u0b95\u0bcd\u0b95\u0bca\u0b95 \u0baa\u0bc1\u0ba4\u0bcd\u0ba4\u0bb3\u0bae\u0bcd \u0bb2\u0bb5\u0ba4\u0bcd\u0ba4\u0bbf\u0baf\u0b9a\u0bca\u0bb2\u0bb2\u0baf\u0bbf\u0ba9\u0bcd \u0baa\u0bbf\u0ba4\u0bb0\u0ba4 \u0b85\u0bb2\u0bb1\u0baf\u0bbf\u0bb2\u0bcd \u0bb2\u0bb5\u0b95\u0bcd\u0b95\u0baa\u0bcd\u0baa\u0b9f\u0bcd\u0b9f\u0bc1\u0bb3\u0bcd\u0bb3\u0ba4\u0bc1\u0b9f\u0ba9\u0bcd, \u0bb5\u0ba9\u0bca\u0ba4\u0bcd\u0ba4\u0bb5\u0bbf\u0bb2\u0bcd\u0bb2\u0bc1 \u0baa\u0baa\u0bca\u0bb2\u0bbf\u0bb8\u0bca\u0bca\u0bcd \u0ba4\u0bae\u0bb2\u0ba4\u0bbf\u0b95 \u0bb5\u0bbf\u0b9a\u0bca\u0bb0\u0bb2\u0bc8\u0b95\u0bb2\u0bb3 \u0ba4\u0bae\u0bb1\u0bcd\u0baa\u0b95\u0bca\u0bc8\u0bcd\u0b9f\u0bc1 \u0bb5\u0bb0\u0bc1\u0b95\u0bbf\u0ba9\u0bcd\u0bb1\u0ba9\u0bca\u0bcd.",
    "fonts": [
      "Kavivanar-Regular",
      "YuGothic-Regular"
    ],
    "sizes": [
      12.0
    ]
  },
  {
    "page_number": 1,
    "bbox": [
      107.42,
      287.44,
      407.59,
      300.72
    ],
    "text": "Homicide Investigation \u2013 Wanathawilluwa Police Division",
    "fonts": [
      "TimesNewRomanPS-BoldMT"
    ],
    "sizes": [
      12.0
    ]
  },
  {
    "page_number": 1,
    "bbox": [
      107.42,
      317.32,
      514.6,
      358.2
    ],
    "text": "Investigations have been initiated by the Wanathawilluwa Police following reports that a man was fatally shot in a cashew plantation located in the Karativu area of the Wanathawilluwa Police Division during the early hours of 09.06.2026.",
    "fonts": [
      "TimesNewRomanPSMT"
    ],
    "sizes": [
      12.0
    ]
  },
  {
    "page_number": 1,
    "bbox": [
      107.42,
      372.64,
      498.58,
      385.92
    ],
    "text": "The deceased has been identified as a 34-year-old resident of the Kalaadiya area.",
    "fonts": [
      "TimesNewRomanPSMT"
    ],
    "sizes": [
      12.0
    ]
  },
  {
    "page_number": 1,
    "bbox": [
      107.42,
      400.5,
      524.75,
      455.18
    ],
    "text": "Preliminary investigations have revealed that the victim was allegedly harvesting cashew nuts from a plantation owned by a private estate company in Karativu when he was confronted by estate security personnel. During the incident, he was reportedly shot with a weapon suspected to be an air rifle, resulting in his death.",
    "fonts": [
      "TimesNewRomanPSMT"
    ],
    "sizes": [
      12.0
    ]
  },
  {
    "page_number": 1,
    "bbox": [
      107.42,
      469.74,
      525.83,
      524.42
    ],
    "text": "In connection with the incident, eight estate security guards have been taken into custody, and four air rifles believed to have been used in the offence have been seized. The suspects, aged between 19 and 41 years, are residents of Athathale, Puttalam, Kalpitiya, and Anuradhapura.",
    "fonts": [
      "TimesNewRomanPSMT"
    ],
    "sizes": [
      12.0
    ]
  },
  {
    "page_number": 1,
    "bbox": [
      107.42,
      538.86,
      515.12,
      565.94
    ],
    "text": "The body has been placed at the Puttalam Hospital mortuary pending a post-mortem examination.",
    "fonts": [
      "TimesNewRomanPSMT"
    ],
    "sizes": [
      12.0
    ]
  },
  {
    "page_number": 1,
    "bbox": [
      107.42,
      580.53,
      468.1,
      593.81
    ],
    "text": "Further investigations are being conducted by the Wanathawilluwa Police.",
    "fonts": [
      "TimesNewRomanPSMT"
    ],
    "sizes": [
      12.0
    ]
  },
  {
    "page_number": 1,
    "bbox": [
      72.02,
      639.96,
      527.07,
      792.86
    ],
    "text": "02. \u0db4\u0dd9\u0db4\u0dbb\u0ddc\u0dba\u0dd2\u0db1\u0dca \u0dd9\u0ddc \u0d85\u0dba\u0dd2\u0dc3\u0dca \u0db8\u0dad\u0dca\u0dbb\u0dd9\u0dba \u0dc3\u0db8\u0d9f \u0dc3\u0dd0 \u0dbb\u0dd4\u0db4\u0dd9\u0d9a\u0dd4 \u0d85\u0dad\u0dca\u0d85\u0da9\u0dd2\u0d82\u0d9c\u0dd4\u0dd9\u0da7 - \u0db4 \u0ddc\u0dbd\u0dd2\u0dc3\u0dca \u0dc0\u0dd2\u0db4\u0dc1\u0dca\u0dc2\u0dca\u200d \u0ddc\u0dbb\u0dca\u0dba \u0db6\u0dbd \u0ddc \u0da2\u0dba\u0dd9\u0dbb\u0dca\u0db0\u0dca\u200d\u0db1\u0db4\u0dd4\u0dbb \u0db3\u0dc0\u0dd4\u0dbb. 2026.06.09 \u0daf\u0dd2\u0db1 \u0dbb\u0dcf\u0dad\u0dca\u200d\u0dbb\u0dd3 \u0dba\u0db8\u0dcf\u0dbb\u0da7\u0dd4\u0dc0 \u0db1\u0d9c\u0dbb\u0dba\u0dda\u0daf\u0dd3 \u0dba \u0dcf\u0dbd\u0dd2\u0dc3\u0dca \u0dc0\u0dd2\u0dba\u0dc1\u0dca\u0dc2 \u0d9a\u0dcf\u0dbb\u0dca\u0dba \u0db6\u0dbd\u0d9a\u0dcf \u0da2\u0dba\u0dc0\u0dbb\u0dca\u0db0\u0db1\u0db4\u0dd4\u0dbb \u0d9a\u0db3\u0dc0\u0dd4\u0dba\u0dbb\u0dca \u0db1\u0dd2\u0dbd\u0db0\u0dcf\u0dbb\u0dd3\u0db1\u0dca \u0d9a\u0dab\u0dca\u0da9\u0dcf\u0dba\u0db8\u0d9a\u0dca \u0dc0\u0dd2\u0dc3\u0dd2\u0db1\u0dca \u0dc0\u0dd0\u0da7\u0dbd\u0dd3\u0db8\u0d9a\u0dca \u0dc3\u0dd2\u0daf\u0dd4\u0d9a\u0dbb \u0dba\u0dc4\u0dba\u0dbb\u0dcf\u0dba\u0dd2\u0db1\u0dca \u0d9c\u0dca\u200d\u0dbb\u0dd1\u0db8\u0dca 52 \u0db8\u0dd2\u0dbd\u0dd2\u0d9c\u0dca\u200d\u0dbb\u0dd1\u0db8\u0dca 610 \u0d9a\u0dca \u0dc4\u0dcf \u0d85\u0dba\u0dd2\u0dc3\u0dca \u0db8\u0dad\u0dca\u0dbb\u0dc0\u0dba \u0d9c\u0dca\u200d\u0dbb\u0dd1\u0db8\u0dca 50 \u0db8\u0dd2\u0dbd\u0dd2\u0d9c\u0dca\u200d\u0dbb\u0dd1\u0db8\u0dca 610 \u0d9a\u0dca \u0dc3\u0db1\u0dca\u0dad\u0d9a\u0dba\u0dda \u0dad\u0db6\u0dcf\u0dba\u0d9c\u0db1 \u0dc3\u0dd2\u0da7\u0dd2 \u0dc3\u0dd0\u0d9a\u0d9a\u0dbb\u0dd4\u0dba\u0dc0\u0d9a\u0dd4 \u0d85\u0dad\u0dca\u0d85\u0da9\u0d82\u0d9c\u0dd4\u0dc0\u0da7 \u0dba\u0d9c\u0db1 \u0dba\u0db8\u0dcf\u0dbb\u0da7\u0dd4\u0dc0 \u0dba \u0dcf\u0dbd\u0dd2\u0dc3\u0dca \u0dc3\u0dca\u0dae\u0dcf\u0db1\u0dba \u0dba\u0dc0\u0dad \u0d89\u0daf\u0dd2\u0dbb\u0dd2 \u0dad\u0dca \u0d9a\u0dbb \u0d87\u0dad. \u0dc3\u0dd0 \u0dbb\u0dd4 \u0dd9\u0dba\u0dc3 \u0d85\u0dc0\u0dd4\u0dbb\u0dd4\u0daf\u0dd4 36\u0d9a\u0dca \u0dd9\u0db1 \u0dbb\u0dad\u0dca\u0db8\u0dbd\u0ddc\u0db1 \u0db4\u0dca\u200d\u0dbb\u0db4\u0dda\u0dc1\u0db4\u0dda \u0daf\u0dd2\u0d82\u0da0\u0dd2 \u0dbb\u0dd4\u0db4\u0dd9\u0d9a\u0dd2.",
    "fonts": [
      "IskoolaPota",
      "IskoolaPota-Bold"
    ],
    "sizes": [
      6.960000038146973,
      14.039999961853027
    ]
  },
  {
    "page_number": 2,
    "bbox": [
      108.02,
      31.82,
      421.96,
      48.07
    ],
    "text": "\u0dba\u0db8\u0dcf\u0dbb\u0da7\u0dd4\u0dc0 \u0dba \u0dcf\u0dbd\u0dd2\u0dc3\u0dd2\u0dba \u0dc0\u0dd2\u0dc3\u0dd2\u0db1\u0dca \u0dc0\u0dd0\u0da9\u0dd2\u0daf\u0dd4\u0dbb \u0dc0\u0dd2\u0db8\u0dbb\u0dca\u0dc1\u0db1 \u0dc3\u0dd2\u0daf\u0dd4 \u0d9a\u0dbb\u0db1\u0dd4 \u0dbd\u0db6\u0dba\u0dd2.",
    "fonts": [
      "IskoolaPota",
      "IskoolaPota-Bold"
    ],
    "sizes": [
      14.039999961853027
    ]
  },
  {
    "page_number": 2,
    "bbox": [
      108.02,
      61.86,
      525.9,
      97.66
    ],
    "text": "\u0baa\u0bc6\u0ba4\u0bb0\u0bca\u0baf\u0bbf\u0ba9\u0bcd \u0bae\u0bb1\u0bcd\u0bb1\u0bc1\u0bae\u0bcd \u0b90\u0bb8\u0bcd \u0ba4\u0baa\u0bca\u0bb2\u0ba4\u0baa\u0bcd\u0baa\u0baa\u0bca\u0bb0\u0bc1\u0bb3\u0bc1\u0b9f\u0ba9\u0bcd \u0b92\u0bb0\u0bc1\u0bb5\u0bca\u0bcd \u0bb2\u0b95\u0ba4\u0bc1 \u2013 \u0baa\u0baa\u0bca\u0bb2\u0bbf\u0bb8\u0bcd \u0bb5\u0bbf\u0ba4\u0b9a\u0b9f \u0b85\u0ba4\u0bbf\u0bb0\u0b9f\u0bbf\u0baa\u0bcd\u0baa\u0bb2\u0b9f, \u0baa\u0bc6\u0baf\u0bb5\u0bca\u0bcd\u0ba4\u0ba9\u0baa\u0bc1\u0bb0 \u0bae\u0bc1\u0b95\u0bca\u0bae\u0bcd",
    "fonts": [
      "Kavivanar-Regular"
    ],
    "sizes": [
      12.0
    ]
  },
  {
    "page_number": 2,
    "bbox": [
      108.02,
      111.56,
      525.94,
      200.62
    ],
    "text": "2026.06.09 \u0b85\u0ba9\u0bcd\u0bb1\u0bc1 \u0b87\u0bb0\u0bb5\u0bc1, \u0baa\u0bae\u0bca\u0bb0\u0b9f\u0bcd\u0b9f\u0bc1\u0bb5 \u0ba8\u0b95\u0bca\u0bbf\u0bb2\u0bcd \u0baa\u0bc6\u0baf\u0bb5\u0bca\u0bcd\u0ba4\u0ba9\u0baa\u0bc1\u0bb0 \u0baa\u0baa\u0bca\u0bb2\u0bbf\u0bb8\u0bcd \u0bb5\u0bbf\u0ba4\u0b9a\u0b9f \u0b85\u0ba4\u0bbf\u0bb0\u0b9f\u0bbf\u0baa\u0bcd\u0baa\u0bb2\u0b9f \u0b85\u0ba4\u0bbf\u0b95\u0bca\u0bca\u0bbf\u0b95\u0bb3\u0bcd \u0ba4\u0bae\u0bb1\u0bcd\u0baa\u0b95\u0bca\u0bc8\u0bcd\u0b9f \u0ba4\u0b9a\u0bca\u0ba4\u0bb2\u0ba9\u0baf\u0bbf\u0ba9\u0bcd \u0ba4\u0baa\u0bca\u0ba4\u0bc1, 52 \u0b95\u0bbf\u0bb0\u0bca\u0bae\u0bcd 610 \u0bae\u0bbf\u0bb2\u0bcd\u0bb2\u0bbf\u0b95\u0bbf\u0bb0\u0bca\u0bae\u0bcd \u0baa\u0bc6\u0ba4\u0bb0\u0bca\u0baf\u0bbf\u0ba9\u0bcd \u0bae\u0bb1\u0bcd\u0bb1\u0bc1\u0bae\u0bcd 50 \u0b95\u0bbf\u0bb0\u0bca\u0bae\u0bcd 610 \u0bae\u0bbf\u0bb2\u0bcd\u0bb2\u0bbf\u0b95\u0bbf\u0bb0\u0bca\u0bae\u0bcd \u0b90\u0bb8\u0bcd \u0ba4\u0baa\u0bca\u0bb2\u0ba4\u0baa\u0bcd\u0baa\u0baa\u0bca\u0bb0\u0bc1\u0bb3\u0bc1\u0b9f\u0ba9\u0bcd \u0b92\u0bb0\u0bc1\u0bb5\u0bca\u0bcd \u0bb2\u0b95\u0ba4\u0bc1 \u0baa\u0b9a\u0baf\u0bcd\u0baf\u0baa\u0bcd\u0baa\u0b9f\u0bcd\u0b9f\u0bc1 \u0baa\u0bae\u0bca\u0bb0\u0b9f\u0bcd\u0b9f\u0bc1\u0bb5 \u0baa\u0baa\u0bca\u0bb2\u0bbf\u0bb8\u0bcd \u0ba8\u0bbf\u0bb2\u0bb2\u0baf\u0ba4\u0bcd\u0ba4\u0bbf\u0bb2\u0bcd \u0b92\u0baa\u0bcd\u0baa\u0bb2\u0b9f\u0b95\u0bcd\u0b95\u0baa\u0bcd\u0baa\u0b9f\u0bcd\u0b9f\u0bc1\u0bb3\u0bcd\u0bb3\u0bca\u0bca\u0bcd.",
    "fonts": [
      "Kavivanar-Regular"
    ],
    "sizes": [
      12.0
    ]
  },
  {
    "page_number": 2,
    "bbox": [
      108.02,
      214.64,
      454.41,
      232.42
    ],
    "text": "\u0b9a\u0ba8\u0bcd\u0ba4\u0ba4\u0b95\u0ba8\u0baa\u0bca\u0bcd 36 \u0bb5\u0baf\u0ba4\u0bc1\u0bb2\u0b9f\u0baf \u0b87\u0bb0\u0ba4\u0bcd\u0bae\u0bb2\u0bca\u0bb2\u0ba9 \u0baa\u0b95\u0bc1\u0ba4\u0bbf\u0bb2\u0baf\u0b9a\u0bcd \u0ba4\u0b9a\u0bca\u0bcd\u0ba8\u0bcd\u0ba4\u0bb5\u0bca\u0bcd.",
    "fonts": [
      "Kavivanar-Regular"
    ],
    "sizes": [
      12.0
    ]
  },
  {
    "page_number": 2,
    "bbox": [
      108.02,
      246.23,
      525.66,
      282.01
    ],
    "text": "\u0baa\u0bae\u0bca\u0bb0\u0b9f\u0bcd\u0b9f\u0bc1\u0bb5 \u0baa\u0baa\u0bca\u0bb2\u0bbf\u0bb8\u0bca\u0bca\u0bcd \u0ba4\u0bae\u0bb2\u0ba4\u0bbf\u0b95 \u0bb5\u0bbf\u0b9a\u0bca\u0bb0\u0bb2\u0bc8\u0b95\u0bb2\u0bb3 \u0ba4\u0bae\u0bb1\u0bcd\u0baa\u0b95\u0bca\u0bc8\u0bcd\u0b9f\u0bc1 \u0bb5\u0bb0\u0bc1\u0b95\u0bbf\u0ba9\u0bcd\u0bb1\u0ba9\u0bca\u0bcd.",
    "fonts": [
      "Kavivanar-Regular",
      "YuGothic-Regular"
    ],
    "sizes": [
      12.0
    ]
  },
  {
    "page_number": 2,
    "bbox": [
      107.42,
      296.44,
      508.74,
      325.56
    ],
    "text": "Suspect Arrested with Heroin and Crystal Methamphetamine \u2013 Police Special Task Force, Jayawardenapura Camp",
    "fonts": [
      "TimesNewRomanPS-BoldMT"
    ],
    "sizes": [
      12.0
    ]
  },
  {
    "page_number": 2,
    "bbox": [
      107.42,
      342.16,
      516.78,
      383.04
    ],
    "text": "A team of officers attached to the Police Special Task Force Jayawardenapura Camp conducted a raid in Moratuwa town on the night of 09.06.2026 and apprehended a suspect found in possession of narcotics.",
    "fonts": [
      "TimesNewRomanPSMT"
    ],
    "sizes": [
      12.0
    ]
  },
  {
    "page_number": 2,
    "bbox": [
      107.42,
      397.48,
      513.91,
      452.18
    ],
    "text": "During the operation, officers recovered 52 grams and 610 milligrams of heroin and 50 grams and 610 milligrams of crystal methamphetamine (commonly known as \u201cice\u201d). The suspect and the seized narcotics were subsequently handed over to the Moratuwa Police Station for further legal proceedings.",
    "fonts": [
      "TimesNewRomanPSMT"
    ],
    "sizes": [
      12.0
    ]
  },
  {
    "page_number": 2,
    "bbox": [
      107.42,
      466.74,
      357.07,
      480.02
    ],
    "text": "The suspect is a 36-year-old resident of Ratmalana.",
    "fonts": [
      "TimesNewRomanPSMT"
    ],
    "sizes": [
      12.0
    ]
  },
  {
    "page_number": 2,
    "bbox": [
      107.42,
      494.58,
      438.46,
      507.86
    ],
    "text": "Further investigations are being carried out by the Moratuwa Police.",
    "fonts": [
      "TimesNewRomanPSMT"
    ],
    "sizes": [
      12.0
    ]
  },
  {
    "page_number": 2,
    "bbox": [
      72.02,
      546.69,
      527.08,
      775.03
    ],
    "text": "03. \u0dc3\u0db8\u0dca\u0db7\u0ddc\u0dd9\u0db1 \u0db8\u0db0\u0dca\u200d\u0dba\u0dc3\u0dca\u0dae\u0ddc\u0db1 \u0db8\u0dd4\u0dd9\u0ddc\u0db4\u0dd9\u0db1\u0dca \u0dd9\u0dad\u0dca\u0dd9\u0ddc\u0db4\u0d9c\u0db1 \u0d9c\u0dd2\u0dba \u0d9c\u0dab\u0dd2 \u0ddc \u0db1\u0dd2\u0dd9\u0ddc\u0dc3 \u0db4\u0daf \u0d9a\u0dca \u0dd9\u0da7\u0dbd\u0ddc \u0dc3\u0dd0 \u0dbb\u0dd4\u0db4\u0dd9\u0d9a\u0dd4 \u0dd9\u0ddc \u0dc3\u0dd0 \u0ddc\u0dbb\u0dd2\u0dba\u0db1\u0dca 12 \u0db4\u0daf\u0db4\u0db1\u0d9a\u0dd4 \u0d85\u0dad\u0dca\u0d85\u0da9\u0dd2\u0d82\u0d9c\u0dd4\u0dd9\u0da7 - \u0dc5\u0dd4\u0dad\u0dbb \u0db4 \u0ddc\u0da7\u0dca\u0da8\u0ddc\u0dc3 \u0d85 \u0dbb\u0ddc\u0db0\u0dca\u200d \u0dc0\u0dd2\u0db8\u0dbb\u0dca\u0dc1\u0db1 \u0ddc\u0dbb\u0dca\u0dba\u0dd2\u0d82\u0dc1\u0dba. 2026.06.09 \u0daf\u0dd2\u0db1 \u0dbb\u0dcf\u0dad\u0dca\u200d\u0dbb\u0dd3 \u0d85\u0dc5\u0dd4\u0dad\u0dca\u0d9c\u0db8 \u0dba \u0dcf\u0dbd\u0dd2\u0dc3\u0dca \u0dc0\u0dc3\u0dba\u0db8\u0dca \u0d85\u0dc5\u0dd4\u0dad\u0dca\u0d9c\u0db8 \u0db1\u0d9c\u0dbb\u0dba\u0dda\u0daf\u0dd3 \u0d9a\u0dc5\u0dd4\u0dad\u0dbb \u0dba\u0d9a\u0dcf\u0da7\u0dca\u0da8\u0dcf\u0dc3 \u0d85 \u0dbb\u0dcf\u0db0 \u0dc0\u0dd2\u0db8\u0dbb\u0dca\u0dc1\u0db1 \u0d9a\u0dcf\u0dbb\u0dca\u0dba\u0d82\u0dc1\u0dba\u0dda \u0db1\u0dd2\u0dbd\u0db0\u0dcf\u0dbb\u0dd3\u0db1\u0dca \u0d9a\u0dab\u0dca\u0da9\u0dcf\u0dba\u0db8\u0d9a\u0dca \u0dc0\u0dd2\u0dc3\u0dd2\u0db1\u0dca \u0dc0\u0dd0\u0da7\u0dbd\u0dd3\u0db8\u0dca \u0dba\u0daf\u0d9a\u0d9a\u0dca \u0dc3\u0dd2\u0daf\u0dd4\u0d9a\u0dbb \u0dc3\u0db8\u0dca\u0db7\u0dcf\u0dc4\u0db1 \u0db8\u0db0\u0dba\u0dc3\u0dca\u0dae\u0dcf\u0db1 \u0db8\u0dd4\u0dc0\u0dcf\u0dba\u0dc0\u0db1\u0dca \u0dc0\u0dad\u0dca\u0dc0\u0dcf\u0dba\u0d9c\u0db1 \u0d9c\u0dd2\u0dba \u0d9c\u0dab\u0dd2\u0d9a\u0dcf \u0db1\u0dd2\u0dc0\u0dcf\u0dc3 02 \u0d9a\u0dca \u0dc0\u0da7\u0dbd\u0dcf \u0d9c\u0dab\u0dd2 \u0ddc \u0db1\u0dd2\u0dd9\u0ddc\u0dc3 \u0dc5\u0db8\u0dab\u0ddc \u0dbb\u0dab\u0dba \u0d9a\u0dd2\u0dbb\u0dd3\u0db8 \u0dc3\u0db8\u0dca\u0db6\u0db1\u0dca\u0db0\u0dca\u200d\u0db4\u0dba\u0db1\u0dca \u0dc3\u0dd0 \u0dbb\u0dd4\u0db4\u0dd9\u0d9a\u0dd4 \u0dd9\u0ddc \u0d9c\u0dab\u0dd2 \u0ddc \u0db4\u0dc3\u0dca\u0dd9\u0dba \u0dc3\u0dd0 \u0dba\u0dd3\u0db8 \u0dc3\u0db3\u0dd9\u0ddc \u0dbb\u0dd0\u0db3\u0dd3 \u0dc3\u0dd2\u0da7\u0dd2 \u0dc3\u0dd0 \u0ddc\u0dbb\u0dd2\u0dba\u0db1\u0dca 12 \u0db4\u0daf\u0db4\u0db1\u0d9a\u0dd4 \u0d85\u0dad\u0dca\u0d85\u0da9\u0dd2\u0d82\u0d9c\u0dd4\u0dd9\u0da7 \u0dba\u0d9c\u0db1 \u0d85\u0dc5\u0dd4\u0dad\u0dca\u0d9c\u0db8 \u0dba \u0dcf\u0dbd\u0dd2\u0dc3\u0dca \u0dc3\u0dca\u0dae\u0dcf\u0db1\u0dba \u0dba\u0dc0\u0dad \u0d89\u0daf\u0dd2\u0dbb\u0dd2 \u0dad\u0dca \u0d9a\u0dbb \u0d87\u0dad. \u0dc3\u0dd0 \u0dbb\u0dd4 \u0dd9\u0dba\u0dc3 \u0d85\u0dc0\u0dd4\u0dbb\u0dd4\u0daf\u0dd4 57 \u0d9a\u0dca \u0dd9\u0db1 \u0d85\u0dc5\u0dd4\u0dad\u0dca\u0d9c\u0db8 \u0db4\u0dca\u200d\u0dbb\u0db4\u0dda\u0dc1\u0db4\u0dda \u0daf\u0dd2\u0d82\u0da0\u0dd2 \u0dbb\u0dd4\u0db4\u0dd9\u0d9a\u0dd4 \u0dd9\u0db1 \u0d85\u0dad\u0dbb \u0dc3\u0dd0 \u0ddc\u0dbb\u0dd2\u0dba\u0db1\u0dca \u0d85\u0dc0\u0dd4\u0dbb\u0dd4\u0daf\u0dd4 23 \u0dad\u0dca 43\u0dad\u0dca \u0d85\u0dad\u0dbb \u0dd9\u0dba\u0dc3\u0dca\u0dd9\u0dbd \u0dc3\u0dd4\u0dd9\u0db1 \u0dad\u0dbd\u0dca\u0dbd\u0d9c\u0dc3\u0dca\u0dd9\u0dbd, \u0db8\u0dad\u0dca\u0dad ,",
    "fonts": [
      "IskoolaPota",
      "IskoolaPota-Bold"
    ],
    "sizes": [
      6.960000038146973,
      14.039999961853027
    ]
  },
  {
    "page_number": 3,
    "bbox": [
      108.02,
      31.82,
      527.06,
      89.13
    ],
    "text": "\u0d87\u0dbd\u0dca\u0dbd\u0dd2\u0da7\u0dd2\u0dba, \u0d9a\u0dd2\u0dbb\u0dd2\u0d87\u0dbd\u0dca\u0dbd\u0dbd, \u0db1\u0dd9\u0db1\u0dca\u0dad\u0dd4\u0da9\u0dd4\u0dd9, \u0d8b\u0da9 \u0dbb\u0dc0\u0dd2\u0da7, \u0dd9\u0ddc\u0dda\u0dd6\u0dd9, \u0db4\u0db8\u0ddc\u0dbb\u0da7\u0dd4\u0dd9, \u0db6\u0daf\u0dd4\u0dbd\u0dca\u0dbd\u0dbd, \u0db8\u0ddc\u0dc3\u0dca\u0db4 \u0ddc\u0dad, \u0db1\u0dd4\u0dd9\u0dbb\u0d91\u0dc5\u0dd2\u0dba \u0dd9\u0ddc \u0db6\u0dd2\u0db6\u0dd2\u0dbd \u0db4\u0dca\u200d\u0dbb\u0db4\u0dda\u0dc1\u0dd9\u0dbd \u0daf\u0dd2\u0d82\u0da0\u0dd2 \u0ddc\u0dbb\u0dd2\u0dba\u0db1\u0dca \u0db4\u0dda. \u0d85\u0dc5\u0dd4\u0dad\u0dca\u0d9c\u0db8 \u0dba \u0dcf\u0dbd\u0dd2\u0dc3\u0dd2\u0dba \u0dc0\u0dd2\u0dc3\u0dd2\u0db1\u0dca \u0dc0\u0dd0\u0da9\u0dd2\u0daf\u0dd4\u0dbb \u0dc0\u0dd2\u0db8\u0dbb\u0dca\u0dc1\u0db1 \u0dc3\u0dd2\u0daf\u0dd4 \u0d9a\u0dbb\u0db1\u0dd4 \u0dbd\u0db6\u0dba\u0dd2.",
    "fonts": [
      "IskoolaPota",
      "IskoolaPota-Bold"
    ],
    "sizes": [
      6.960000038146973,
      14.039999961853027
    ]
  },
  {
    "page_number": 3,
    "bbox": [
      108.02,
      102.92,
      525.85,
      138.7
    ],
    "text": "\u0bae\u0b9a\u0bca\u0bc6\u0bcd \u0ba8\u0bbf\u0bb2\u0bb2\u0baf\u0b99\u0bcd\u0b95\u0bb3\u0bcd \u0b8e\u0ba9\u0bcd\u0bb1 \u0baa\u0baa\u0baf\u0bca\u0bbf\u0bb2\u0bcd \u0b87\u0baf\u0b99\u0bcd\u0b95\u0bbf\u0baf \u0b87\u0bb0\u0bc8\u0bcd\u0b9f\u0bc1 \u0bb5\u0bbf\u0baa\u0b9a\u0bcd\u0b9a\u0bca\u0bb0 \u0bb5\u0bbf\u0b9f\u0bc1\u0ba4\u0bbf\u0b95\u0bb3\u0bcd \u0b9a\u0bc1\u0bb1\u0bcd\u0bb1\u0bbf\u0bb5\u0bb2\u0bb3\u0baa\u0bcd\u0baa\u0bc1 \u2013 \u0b92\u0bb0\u0bc1\u0bb5\u0bca\u0bcd \u0bae\u0bb1\u0bcd\u0bb1\u0bc1\u0bae\u0bcd 12 \u0baa\u0baa\u0bc8\u0bcd\u0b95\u0bb3\u0bcd \u0bb2\u0b95\u0ba4\u0bc1",
    "fonts": [
      "Kavivanar-Regular"
    ],
    "sizes": [
      12.0
    ]
  },
  {
    "page_number": 3,
    "bbox": [
      108.02,
      152.6,
      525.92,
      223.78
    ],
    "text": "2026.06.09 \u0b85\u0ba9\u0bcd\u0bb1\u0bc1 \u0b87\u0bb0\u0bb5\u0bc1, \u0b85\u0bb2\u0bc1\u0ba4\u0bcd\u0b95\u0bae \u0ba8\u0b95\u0bca\u0bbf\u0bb2\u0bcd \u0b95\u0bb2\u0bc1\u0ba4\u0bcd\u0ba4\u0bc1\u0bb2\u0bb1 \u0baa\u0bbf\u0bca\u0bbf\u0bb5\u0bc1 \u0b95\u0bc1\u0bb1\u0bcd\u0bb1\u0baa\u0bcd \u0baa\u0bc1\u0bb2\u0ba9\u0bca\u0baf\u0bcd\u0bb5\u0bc1 \u0baa\u0bbf\u0bca\u0bbf\u0bb5\u0bc1 \u0b85\u0ba4\u0bbf\u0b95\u0bca\u0bca\u0bbf\u0b95\u0bb3\u0bcd \u0b87\u0bb0\u0bc8\u0bcd\u0b9f\u0bc1 \u0ba4\u0b9a\u0bca\u0ba4\u0bb2\u0ba9\u0b95\u0bb2\u0bb3 \u0ba4\u0bae\u0bb1\u0bcd\u0baa\u0b95\u0bca\u0bc8\u0bcd\u0b9f\u0bc1, \u0bae\u0b9a\u0bca\u0bc6\u0bcd \u0ba8\u0bbf\u0bb2\u0bb2\u0baf\u0b99\u0bcd\u0b95\u0bb3\u0bcd \u0b8e\u0ba9\u0bcd\u0bb1 \u0baa\u0baa\u0baf\u0bca\u0bbf\u0bb2\u0bcd \u0b87\u0baf\u0b99\u0bcd\u0b95\u0bbf\u0baf \u0b87\u0bb0\u0bc8\u0bcd\u0b9f\u0bc1 \u0bb5\u0bbf\u0baa\u0b9a\u0bcd\u0b9a\u0bca\u0bb0 \u0bb5\u0bbf\u0b9f\u0bc1\u0ba4\u0bbf\u0b95\u0bb2\u0bb3 \u0bae\u0bc1\u0bb1\u0bcd\u0bb1\u0bc1\u0bb2\u0b95\u0baf\u0bbf\u0b9f\u0bcd\u0b9f\u0ba9\u0bca\u0bcd.",
    "fonts": [
      "Kavivanar-Regular"
    ],
    "sizes": [
      12.0
    ]
  },
  {
    "page_number": 3,
    "bbox": [
      108.02,
      237.71,
      525.93,
      291.13
    ],
    "text": "\u0b87\u0ba4\u0ba9\u0bcd\u0ba4\u0baa\u0bca\u0ba4\u0bc1, \u0bb5\u0bbf\u0b9f\u0bc1\u0ba4\u0bbf\u0b95\u0bb2\u0bb3 \u0ba8\u0bbf\u0bca\u0bcd\u0bb5\u0b95\u0bbf\u0ba4\u0bcd\u0ba4\u0ba4\u0bca\u0b95\u0b95\u0bcd \u0b95\u0bc2\u0bb1\u0baa\u0bcd\u0baa\u0b9f\u0bc1\u0bae\u0bcd 57 \u0bb5\u0baf\u0ba4\u0bc1\u0bb2\u0b9f\u0baf \u0b92\u0bb0\u0bc1\u0bb5\u0bb0\u0bc1\u0bae\u0bcd, \u0baa\u0bca\u0bb2\u0bbf\u0baf\u0bb2\u0bcd \u0ba4\u0b9a\u0bb2\u0bb5\u0b95\u0bcd\u0b95\u0bca\u0b95 \u0ba4\u0b99\u0bcd\u0b95\u0bbf\u0baf\u0bbf\u0bb0\u0bc1\u0ba8\u0bcd\u0ba4 12 \u0baa\u0baa\u0bc8\u0bcd\u0b95\u0bb3\u0bc1\u0bae\u0bcd \u0bb2\u0b95\u0ba4\u0bc1 \u0baa\u0b9a\u0baf\u0bcd\u0baf\u0baa\u0bcd\u0baa\u0b9f\u0bcd\u0b9f\u0bc1 \u0b85\u0bb2\u0bc1\u0ba4\u0bcd\u0b95\u0bae \u0baa\u0baa\u0bca\u0bb2\u0bbf\u0bb8\u0bcd \u0ba8\u0bbf\u0bb2\u0bb2\u0baf\u0ba4\u0bcd\u0ba4\u0bbf\u0bb2\u0bcd \u0b92\u0baa\u0bcd\u0baa\u0bb2\u0b9f\u0b95\u0bcd\u0b95\u0baa\u0bcd\u0baa\u0b9f\u0bcd\u0b9f\u0bc1\u0bb3\u0bcd\u0bb3\u0ba9\u0bca\u0bcd.",
    "fonts": [
      "Kavivanar-Regular"
    ],
    "sizes": [
      12.0
    ]
  },
  {
    "page_number": 3,
    "bbox": [
      108.02,
      305.03,
      525.93,
      376.33
    ],
    "text": "\u0baa\u0baa\u0bc8\u0bcd\u0b95\u0bb3\u0bcd 23 \u0bae\u0bc1\u0ba4\u0bb2\u0bcd 43 \u0bb5\u0baf\u0ba4\u0bc1\u0b95\u0bcd\u0b95\u0bc1\u0b9f\u0bcd\u0baa\u0b9f\u0bcd\u0b9f\u0bb5\u0bca\u0bcd\u0b95\u0bb3\u0bca\u0b95\u0bb5\u0bc1\u0bae\u0bcd, \u0ba4\u0bb2\u0bcd\u0b95\u0bb8\u0bcd\u0bb5\u0bb2, \u0bae\u0ba4\u0bcd\u0ba4\u0b95, \u0b8e\u0bb2\u0bcd\u0baa\u0bbf\u0b9f\u0bcd\u0b9f\u0bbf\u0baf, \u0b95\u0bbf\u0bca\u0bbf\u0baa\u0baf\u0bb2\u0bcd\u0bb2, \u0ba8\u0bb5\u0ba8\u0bcd\u0ba4\u0bc1\u0b9f\u0bc1\u0bb5, \u0b89\u0b9f\u0b95\u0bb0\u0bb5\u0bbf\u0b9f\u0bcd\u0b9f, \u0bb5\u0bca\u0ba4\u0bcd\u0ba4\u0bc1\u0bb2\u0bb5, \u0baa\u0bae\u0bca\u0bb0\u0b9f\u0bcd\u0b9f\u0bc1\u0bb5, \u0baa\u0ba4\u0bc1\u0bb2\u0bb3, \u0bae\u0bca\u0bb8\u0bcd\u0baa\u0baa\u0bca\u0ba4\u0bcd\u0ba4, \u0ba8\u0bc1\u0bb5\u0baa\u0bb0\u0bb2\u0bbf\u0baf\u0bca \u0bae\u0bb1\u0bcd\u0bb1\u0bc1\u0bae\u0bcd \u0baa\u0bbf\u0baa\u0bbf\u0bb2 \u0baa\u0b95\u0bc1\u0ba4\u0bbf\u0b95\u0bb2\u0bb3\u0b9a\u0bcd \u0ba4\u0b9a\u0bca\u0bcd\u0ba8\u0bcd\u0ba4\u0bb5\u0bca\u0bcd\u0b95\u0bb3\u0bca\u0b95\u0bb5\u0bc1\u0bae\u0bcd \u0b89\u0bb3\u0bcd\u0bb3\u0ba9\u0bca\u0bcd.",
    "fonts": [
      "Kavivanar-Regular"
    ],
    "sizes": [
      12.0
    ]
  },
  {
    "page_number": 3,
    "bbox": [
      108.02,
      390.18,
      523.35,
      408.13
    ],
    "text": "\u0b85\u0bb2\u0bc1\u0ba4\u0bcd\u0b95\u0bae \u0baa\u0baa\u0bca\u0bb2\u0bbf\u0bb8\u0bca\u0bca\u0bcd \u0ba4\u0bae\u0bb2\u0ba4\u0bbf\u0b95 \u0bb5\u0bbf\u0b9a\u0bca\u0bb0\u0bb2\u0bc8\u0b95\u0bb2\u0bb3 \u0ba4\u0bae\u0bb1\u0bcd\u0baa\u0b95\u0bca\u0bc8\u0bcd\u0b9f\u0bc1 \u0bb5\u0bb0\u0bc1\u0b95\u0bbf\u0ba9\u0bcd\u0bb1\u0ba9\u0bca\u0bcd.",
    "fonts": [
      "Kavivanar-Regular",
      "YuGothic-Regular"
    ],
    "sizes": [
      12.0
    ]
  },
  {
    "page_number": 3,
    "bbox": [
      107.42,
      422.58,
      520.9,
      451.7
    ],
    "text": "Two Brothels Operating Under the Guise of Massage Parlours Raided; Thirteen Persons Arrested \u2013 Kalutara Divisional Criminal Investigation Bureau",
    "fonts": [
      "TimesNewRomanPS-BoldMT"
    ],
    "sizes": [
      12.0
    ]
  },
  {
    "page_number": 3,
    "bbox": [
      107.42,
      468.3,
      521.4,
      509.18
    ],
    "text": "Officers attached to the Kalutara Divisional Criminal Investigation Bureau conducted two separate raids in Aluthgama town within the Aluthgama Police Division on the night of 09.06.2026.",
    "fonts": [
      "TimesNewRomanPSMT"
    ],
    "sizes": [
      12.0
    ]
  },
  {
    "page_number": 3,
    "bbox": [
      107.42,
      523.62,
      526.14,
      592.13
    ],
    "text": "During the operation, two establishments allegedly operating as brothels under the guise of massage parlours were raided. A 57-year-old suspect believed to be involved in the management of the establishments, along with twelve women allegedly engaged in prostitution-related activities, were arrested and handed over to the Aluthgama Police Station.",
    "fonts": [
      "TimesNewRomanPSMT"
    ],
    "sizes": [
      12.0
    ]
  },
  {
    "page_number": 3,
    "bbox": [
      107.42,
      606.69,
      513.17,
      661.37
    ],
    "text": "The male suspect is a resident of Aluthgama. The female suspects, aged between 23 and 43 years, are residents of Thalgaswala, Mattaka, Elpitiya, Kiriella, Navanthuduwa, Udakarawita, Wadduwa, Moratuwa, Badulla, Maspotha, Nuwara Eliya, and Bibile.",
    "fonts": [
      "TimesNewRomanPSMT"
    ],
    "sizes": [
      12.0
    ]
  },
  {
    "page_number": 3,
    "bbox": [
      107.42,
      675.93,
      440.02,
      689.21
    ],
    "text": "Further investigations are being conducted by the Aluthgama Police.",
    "fonts": [
      "TimesNewRomanPSMT"
    ],
    "sizes": [
      12.0
    ]
  },
  {
    "page_number": 3,
    "bbox": [
      72.02,
      703.56,
      526.94,
      776.35
    ],
    "text": "04. \u0db4\u0d9c\u0ddd\u0da9\u0ddc \u0dc3\u0db8\u0d9f \u0dc3\u0dd0 \u0dbb\u0dd4\u0db4\u0dd9\u0d9a\u0dd4 \u0d85\u0dad\u0dca\u0d85\u0da9\u0dd2\u0d82\u0d9c\u0dd4\u0dd9\u0da7 - \u0db8\u0dd9\u0db6\u0ddc\u0db4\u0dda \u0db4 \u0ddc\u0dbd\u0dd2\u0dc3\u0dca \u0dc3\u0dca\u0dae\u0ddc\u0db1\u0dba. 2026.06.09 \u0daf\u0dd2\u0db1 \u0dc3\u0dc0\u0dc3 \u0db8\u0dc4\u0db6\u0dcf\u0dba\u0dda \u0dba \u0dcf\u0dbd\u0dd2\u0dc3\u0dca \u0dc0\u0dc3\u0dba\u0db8\u0dca \u0dba\u0dad\u0dcf\u0da7\u0dd4 \u0dbd \u0dcf\u0dbb \u0db4\u0dca\u200d\u0dbb\u0dba\u0dda\u0dc1\u0dba\u0dda\u0daf\u0dd3 \u0db8\u0dc4\u0db6\u0dcf\u0dba\u0dda \u0dba \u0dcf\u0dbd\u0dd2\u0dc3\u0dca \u0dc3\u0dca\u0dae\u0dcf\u0db1\u0dba\u0dda \u0db1\u0dd2\u0dbd\u0db0\u0dcf\u0dbb\u0dd3\u0db1\u0dca \u0d9a\u0dab\u0dca\u0da9\u0dcf\u0dba\u0db8\u0d9a\u0dca \u0dc0\u0dd2\u0dc3\u0dd2\u0db1\u0dca \u0dc0\u0dd0\u0da7\u0dbd\u0dd3\u0db8\u0d9a\u0dca \u0dc3\u0dd2\u0daf\u0dd4\u0d9a\u0dbb",
    "fonts": [
      "IskoolaPota",
      "IskoolaPota-Bold"
    ],
    "sizes": [
      6.960000038146973,
      14.039999961853027
    ]
  },
  {
    "page_number": 4,
    "bbox": [
      72.02,
      31.82,
      526.82,
      113.61
    ],
    "text": "\u0db1\u0dd3\u0dad\u0dd2 \u0dc0\u0dd2\u0db4\u0dbb\u0ddd\u0db0\u0dd3 \u0db8\u0dad\u0dca \u0dd0\u0db1\u0dca \u0db4 \u0dbb\u0dd3\u0db8\u0da7 \u0d9c\u0db1\u0dca\u0db1\u0ddc \u0db4\u0d9c\u0ddd\u0da9\u0ddc \u0dbd\u0dd3\u0da7\u0dbb\u0dca 1186 \u0d9a\u0dca (\u0db6\u0dd0\u0dbb\u0dbd\u0dca\u0dbd 07\u0d9a\u0dca) \u0dc3\u0db8\u0d9f \u0dc3\u0dd0 \u0dbb\u0dd4\u0db4\u0dd9\u0d9a\u0dd4 \u0d85\u0dad\u0dca\u0d85\u0da9\u0d82\u0d9c\u0dd4\u0dc0\u0da7 \u0dba\u0d9c\u0db1 \u0d87\u0dad. \u0dc3\u0dd0 \u0dbb\u0dd4 \u0dd9\u0dba\u0dc3 \u0d85\u0dc0\u0dd4\u0dbb\u0dd4\u0daf\u0dd4 55\u0d9a\u0dca \u0dd9\u0db1 \u0dd9\u0dd0\u0dbd\u0dd2\u0dc3\u0dbb \u0db4\u0dca\u200d\u0dbb\u0db4\u0dda\u0dc1\u0db4\u0dda \u0daf\u0dd2\u0d82\u0da0\u0dd2 \u0dbb\u0dd4\u0db4\u0dd9\u0d9a\u0dd2. \u0db8\u0dc4\u0db6\u0dcf\u0dba\u0dda \u0dba \u0dcf\u0dbd\u0dd2\u0dc3\u0dd2\u0dba \u0dc0\u0dd2\u0dc3\u0dd2\u0db1\u0dca \u0dc0\u0dd0\u0da9\u0dd2\u0daf\u0dd4\u0dbb \u0dc0\u0dd2\u0db8\u0dbb\u0dca\u0dc1\u0db1 \u0dc3\u0dd2\u0daf\u0dd4 \u0d9a\u0dbb\u0db1\u0dd4 \u0dbd\u0db6\u0dba\u0dd2.",
    "fonts": [
      "IskoolaPota",
      "IskoolaPota-Bold"
    ],
    "sizes": [
      6.960000038146973,
      14.039999961853027
    ]
  },
  {
    "page_number": 4,
    "bbox": [
      108.02,
      127.52,
      428.73,
      145.54
    ],
    "text": "\u0b9a\u0b9f\u0bcd\u0b9f\u0bb5\u0bbf\u0ba4\u0bb0\u0bca\u0ba4 \u0ba4\u0b95\u0bca\u0b9f\u0bb5\u0bc1\u0b9f\u0ba9\u0bcd \u0b92\u0bb0\u0bc1\u0bb5\u0bca\u0bcd \u0bb2\u0b95\u0ba4\u0bc1 \u2013 \u0bae\u0bc6\u0baa\u0bca\u0ba4\u0b95 \u0baa\u0baa\u0bca\u0bb2\u0bbf\u0bb8\u0bcd",
    "fonts": [
      "Kavivanar-Regular"
    ],
    "sizes": [
      12.0
    ]
  },
  {
    "page_number": 4,
    "bbox": [
      108.02,
      159.2,
      525.84,
      230.5
    ],
    "text": "2026.06.09 \u0b85\u0ba9\u0bcd\u0bb1\u0bc1 \u0bae\u0bca\u0bb2\u0bb2, \u0bae\u0bc6\u0baa\u0bca\u0ba4\u0b95 \u0baa\u0baa\u0bca\u0bb2\u0bbf\u0bb8\u0bcd \u0baa\u0bbf\u0bca\u0bbf\u0bb5\u0bbf\u0ba9\u0bcd \u0baa\u0ba4\u0bca\u0b9f\u0bcd\u0b9f\u0bc1\u0baa\u0bca\u0bb2 \u0bb5\u0bc0\u0ba4\u0bbf \u0baa\u0b95\u0bc1\u0ba4\u0bbf\u0baf\u0bbf\u0bb2\u0bcd \u0ba4\u0bae\u0bb1\u0bcd\u0baa\u0b95\u0bca\u0bb3\u0bcd\u0bb3\u0baa\u0bcd\u0baa\u0b9f\u0bcd\u0b9f \u0ba4\u0b9a\u0bca\u0ba4\u0bb2\u0ba9\u0baf\u0bbf\u0bb2\u0bcd, \u0b9a\u0b9f\u0bcd\u0b9f\u0bb5\u0bbf\u0ba4\u0bb0\u0bca\u0ba4 \u0bae\u0ba4\u0bc1\u0baa\u0bca\u0ba9 \u0b89\u0bb1\u0bcd\u0baa\u0ba4\u0bcd\u0ba4\u0bbf\u0b95\u0bcd\u0b95\u0bca\u0b95 \u0baa\u0baf\u0ba9\u0bcd\u0baa\u0b9f\u0bc1\u0ba4\u0bcd\u0ba4\u0baa\u0bcd\u0baa\u0b9f\u0bcd\u0b9f 1,186 \u0bb2\u0bc0\u0bb1\u0bcd\u0bb1\u0bca\u0bcd \u0ba4\u0b95\u0bca\u0b9f\u0bca (07 \u0ba4\u0baa\u0bb0\u0bb2\u0bcd\u0b95\u0bb3\u0bcd) \u0b89\u0b9f\u0ba9\u0bcd \u0b92\u0bb0\u0bc1\u0bb5\u0bca\u0bcd \u0bb2\u0b95\u0ba4\u0bc1 \u0baa\u0b9a\u0baf\u0bcd\u0baf\u0baa\u0bcd\u0baa\u0b9f\u0bcd\u0b9f\u0bc1\u0bb3\u0bcd\u0bb3\u0bca\u0bca\u0bcd.",
    "fonts": [
      "Kavivanar-Regular"
    ],
    "sizes": [
      12.0
    ]
  },
  {
    "page_number": 4,
    "bbox": [
      108.02,
      244.55,
      423.21,
      262.33
    ],
    "text": "\u0b9a\u0ba8\u0bcd\u0ba4\u0ba4\u0b95\u0ba8\u0baa\u0bca\u0bcd 55 \u0bb5\u0baf\u0ba4\u0bc1\u0bb2\u0b9f\u0baf \u0baa\u0bb5\u0bb2\u0bbf\u0b9a\u0bb0 \u0baa\u0b95\u0bc1\u0ba4\u0bbf\u0bb2\u0baf\u0b9a\u0bcd \u0ba4\u0b9a\u0bca\u0bcd\u0ba8\u0bcd\u0ba4\u0bb5\u0bca\u0bcd.",
    "fonts": [
      "Kavivanar-Regular"
    ],
    "sizes": [
      12.0
    ]
  },
  {
    "page_number": 4,
    "bbox": [
      108.02,
      276.18,
      526.11,
      294.13
    ],
    "text": "\u0bae\u0bc6\u0baa\u0bca\u0ba4\u0b95 \u0baa\u0baa\u0bca\u0bb2\u0bbf\u0bb8\u0bca\u0bca\u0bcd \u0ba4\u0bae\u0bb2\u0ba4\u0bbf\u0b95 \u0bb5\u0bbf\u0b9a\u0bca\u0bb0\u0bb2\u0bc8\u0b95\u0bb2\u0bb3 \u0ba4\u0bae\u0bb1\u0bcd\u0baa\u0b95\u0bca\u0bc8\u0bcd\u0b9f\u0bc1 \u0bb5\u0bb0\u0bc1\u0b95\u0bbf\u0ba9\u0bcd\u0bb1\u0ba9\u0bca\u0bcd.",
    "fonts": [
      "Kavivanar-Regular",
      "YuGothic-Regular"
    ],
    "sizes": [
      12.0
    ]
  },
  {
    "page_number": 4,
    "bbox": [
      107.42,
      308.44,
      405.79,
      321.72
    ],
    "text": "Suspect Arrested with \u201cGoda\u201d \u2013 Mahabage Police Station",
    "fonts": [
      "TimesNewRomanPS-BoldMT"
    ],
    "sizes": [
      11.039999961853027,
      12.0
    ]
  },
  {
    "page_number": 4,
    "bbox": [
      107.42,
      338.32,
      524.66,
      393.0
    ],
    "text": "On the evening of 09.06.2026, officers attached to the Mahabage Police Station conducted a raid in the Thotupala Road area within the Mahabage Police Division and apprehended a suspect in possession of 1,186 litres (07 barrels) of \u201cGoda,\u201d an illicit substance used in the production of illegal liquor.",
    "fonts": [
      "TimesNewRomanPSMT"
    ],
    "sizes": [
      12.0
    ]
  },
  {
    "page_number": 4,
    "bbox": [
      107.42,
      407.58,
      389.11,
      420.86
    ],
    "text": "The suspect is a 55-year-old resident of the Welisara area.",
    "fonts": [
      "TimesNewRomanPSMT"
    ],
    "sizes": [
      12.0
    ]
  },
  {
    "page_number": 4,
    "bbox": [
      107.42,
      435.42,
      436.66,
      448.7
    ],
    "text": "Further investigations are being conducted by the Mahabage Police.",
    "fonts": [
      "TimesNewRomanPSMT"
    ],
    "sizes": [
      12.0
    ]
  },
  {
    "page_number": 4,
    "bbox": [
      72.02,
      494.85,
      527.07,
      688.81
    ],
    "text": "05. \u0db1\u0dd3\u0dad\u0dd2\u0dc0\u0dd2\u0db4\u0dbb\u0ddd\u0db0\u0dd3 \u0db8\u0dad\u0dca \u0dd0\u0db1\u0dca \u0dc3\u0db8\u0d9f \u0dc3\u0dd0 \u0dbb\u0dd4\u0db4\u0dd9\u0d9a\u0dd4 \u0d85\u0dad\u0dca\u0d85\u0da9\u0dd2\u0d82\u0d9c\u0dd4\u0dd9\u0da7 - \u0dd9\u0dbd\u0ddc\u0db1 \u0db8\u0db0\u0dca\u200d\u0dba\u0db8 \u0dd6\u0dc2\u0dca\u200d\u0dab \u0db8\u0dbb\u0dca\u0db0\u0dca\u200d\u0db1 \u0db4\u0dca\u200d\u0dbb\u0dd9\u0ddc\u0dbb \u0d92 \u0dba. 2026.06.09 \u0daf\u0dd2\u0db1 \u0d8b\u0daf\u0dd1\u0dc3\u0db1 \u0d9a\u0dd2\u0dbb\u0dd2\u0db6\u0dad\u0dca\u0dba\u0d9c\u0dcf\u0da9 \u0dba \u0dcf\u0dbd\u0dd2\u0dc3\u0dca \u0dc0\u0dc3\u0dba\u0db8\u0dca \u0db1\u0dcf\u0dba\u0dc4\u0dca\u0db1 \u0db4\u0dca\u200d\u0dbb\u0dba\u0dda\u0dc1\u0dba\u0dda\u0daf\u0dd3 \u0dc0\u0dbd\u0dcf\u0db1 \u0db8\u0db0\u0dba\u0db8 \u0daf\u0dd6\u0dc2\u0dab \u0db8\u0dbb\u0dca\u0db0\u0db1 \u0db4\u0dca\u200d\u0dbb\u0dc4\u0dcf\u0dbb\u0d9a \u0d92\u0d9a\u0d9a\u0dba\u0dda \u0db1\u0dd2\u0dbd\u0db0\u0dcf\u0dbb\u0dd3\u0db1\u0dca \u0d9a\u0db1\u0dca\u0da9\u0dcf\u0dba\u0db8\u0d9a\u0dca \u0dc0\u0dd2\u0dc3\u0dd2\u0db1\u0dca \u0dc0\u0dd0\u0da7\u0dbd\u0dd3\u0db8\u0d9a\u0dca \u0dc3\u0dd2\u0daf\u0dd4\u0d9a\u0dbb \u0db1\u0dd3\u0dad\u0dd2 \u0dc0\u0dd2\u0db4\u0dbb\u0ddd\u0db0\u0dd3 \u0db8\u0dad\u0dca \u0dd0\u0db1\u0dca \u0dbd\u0dd3\u0da7\u0dbb\u0dca 76 \u0d9a\u0dca (\u0db4\u0db6\u0ddd\u0dad\u0dbd\u0dca\u0dbd 102) \u0dc3\u0db8\u0d9f \u0dc3\u0dd0 \u0dbb\u0dd4\u0db4\u0dd9\u0d9a\u0dd4 \u0d85\u0dad\u0dca\u0d85\u0da9\u0dd2\u0d82\u0d9c\u0dd4\u0dd9\u0da7 \u0dba\u0d9c\u0db1 \u0d9a\u0dd2\u0dbb\u0dd2\u0db6\u0dad\u0dca\u0dba\u0d9c\u0dcf\u0da9 \u0dba \u0dcf\u0dbd\u0dd2\u0dc3\u0dca \u0dc3\u0dca\u0dae\u0dcf\u0db1\u0dba \u0dba\u0dc0\u0dad \u0d89\u0daf\u0dd2\u0dbb\u0dd2 \u0dad\u0dca \u0d9a\u0dbb \u0d87\u0dad. \u0dc3\u0dd0 \u0dbb\u0dd4 \u0dd9\u0dba\u0dc3 \u0d85\u0dc0\u0dd4\u0dbb\u0dd4\u0daf\u0dd4 38 \u0d9a\u0dca \u0dd9\u0db1 \u0dd9\u0dad\u0dca\u0dad\u0dbd \u0db4\u0dca\u200d\u0dbb\u0db4\u0dda\u0dc1\u0db4\u0dda \u0daf\u0dd2\u0d82\u0da0\u0dd2 \u0dbb\u0dd4\u0db4\u0dd9\u0d9a\u0dd2. \u0d9a\u0dd2\u0dbb\u0dd2\u0db6\u0dad\u0dca\u0dba\u0d9c\u0dcf\u0da9 \u0dba \u0dcf\u0dbd\u0dd2\u0dc3\u0dd2\u0dba \u0dc0\u0dd2\u0dc3\u0dd2\u0db1\u0dca \u0dc0\u0dd0\u0da9\u0dd2\u0daf\u0dd4\u0dbb \u0dc0\u0dd2\u0db8\u0dbb\u0dca\u0dc1\u0db1 \u0dc3\u0dd2\u0daf\u0dd4 \u0d9a\u0dbb\u0db1\u0dd4 \u0dbd\u0db6\u0dba\u0dd2.",
    "fonts": [
      "IskoolaPota",
      "IskoolaPota-Bold",
      "Latha,Bold"
    ],
    "sizes": [
      6.960000038146973,
      14.039999961853027
    ]
  },
  {
    "page_number": 4,
    "bbox": [
      72.02,
      685.08,
      258.35,
      750.91
    ],
    "text": "\u0db4 \u0ddc\u0dbd\u0dd2\u0dc3\u0dca \u0db8\u0ddc\u0db0\u0dca\u200d\u0dba \u0db4 \u0ddc\u0da7\u0dca\u0da8\u0ddc\u0dc3\u0dba.",
    "fonts": [
      "IskoolaPota-Bold"
    ],
    "sizes": [
      14.039999961853027
    ]
  },
  {
    "page_number": 5,
    "bbox": [
      108.02,
      31.38,
      525.75,
      67.16
    ],
    "text": "\u0b9a\u0b9f\u0bcd\u0b9f\u0bb5\u0bbf\u0ba4\u0bb0\u0bca\u0ba4 \u0bae\u0ba4\u0bc1\u0baa\u0bca\u0ba9\u0ba4\u0bcd\u0ba4\u0bc1\u0b9f\u0ba9\u0bcd \u0b92\u0bb0\u0bc1\u0bb5\u0bca\u0bcd \u0bb2\u0b95\u0ba4\u0bc1 \u2013 \u0bb5\u0bb2\u0bca\u0ba9 \u0bae\u0ba4\u0bcd\u0ba4\u0bbf\u0baf \u0b8a\u0bb4\u0bb2\u0bcd \u0b92\u0bb4\u0bbf\u0baa\u0bcd\u0baa\u0bc1 \u0baa\u0bbf\u0bca\u0bbf\u0bb5\u0bc1",
    "fonts": [
      "Kavivanar-Regular"
    ],
    "sizes": [
      12.0
    ]
  },
  {
    "page_number": 5,
    "bbox": [
      108.02,
      81.08,
      525.79,
      170.02
    ],
    "text": "2026.06.09 \u0b85\u0ba9\u0bcd\u0bb1\u0bc1 \u0b95\u0bca\u0bb2\u0bb2, \u0b95\u0bbf\u0bca\u0bbf\u0baa\u0ba4\u0bcd\u0baa\u0b95\u0bca\u0b9f \u0baa\u0baa\u0bca\u0bb2\u0bbf\u0bb8\u0bcd \u0baa\u0bbf\u0bca\u0bbf\u0bb5\u0bbf\u0bb1\u0bcd\u0b95\u0bc1\u0b9f\u0bcd\u0baa\u0b9f\u0bcd\u0b9f \u0ba8\u0bca\u0ba4\u0bc6\u0ba9 \u0baa\u0b95\u0bc1\u0ba4\u0bbf\u0baf\u0bbf\u0bb2\u0bcd, \u0bb5\u0bb2\u0bca\u0ba9 \u0bae\u0ba4\u0bcd\u0ba4\u0bbf\u0baf \u0b8a\u0bb4\u0bb2\u0bcd \u0b92\u0bb4\u0bbf\u0baa\u0bcd\u0baa\u0bc1 \u0baa\u0bbf\u0bca\u0bbf\u0bb5\u0bc1 \u0b85\u0ba4\u0bbf\u0b95\u0bca\u0bca\u0bbf\u0b95\u0bb3\u0bcd \u0ba4\u0bae\u0bb1\u0bcd\u0baa\u0b95\u0bca\u0bc8\u0bcd\u0b9f \u0ba4\u0b9a\u0bca\u0ba4\u0bb2\u0ba9\u0baf\u0bbf\u0bb2\u0bcd, 76 \u0bb2\u0bbf\u0b9f\u0bcd\u0b9f\u0bca\u0bcd \u0b9a\u0b9f\u0bcd\u0b9f\u0bb5\u0bbf\u0ba4\u0bb0\u0bca\u0ba4 \u0bae\u0ba4\u0bc1\u0baa\u0bca\u0ba9\u0bae\u0bcd (102 \u0ba4\u0baa\u0bca\u0ba4\u0bcd\u0ba4\u0bb2\u0bcd\u0b95\u0bb3\u0bcd) \u0b89\u0b9f\u0ba9\u0bcd \u0b92\u0bb0\u0bc1\u0bb5\u0bca\u0bcd \u0bb2\u0b95\u0ba4\u0bc1 \u0baa\u0b9a\u0baf\u0bcd\u0baf\u0baa\u0bcd\u0baa\u0b9f\u0bcd\u0b9f\u0bc1 \u0b95\u0bbf\u0bca\u0bbf\u0baa\u0ba4\u0bcd\u0baa\u0b95\u0bca\u0b9f \u0baa\u0baa\u0bca\u0bb2\u0bbf\u0bb8\u0bcd \u0ba8\u0bbf\u0bb2\u0bb2\u0baf\u0ba4\u0bcd\u0ba4\u0bbf\u0bb2\u0bcd \u0b92\u0baa\u0bcd\u0baa\u0bb2\u0b9f\u0b95\u0bcd\u0b95\u0baa\u0bcd\u0baa\u0b9f\u0bcd\u0b9f\u0bc1\u0bb3\u0bcd\u0bb3\u0bca\u0bca\u0bcd.",
    "fonts": [
      "Kavivanar-Regular"
    ],
    "sizes": [
      12.0
    ]
  },
  {
    "page_number": 5,
    "bbox": [
      108.02,
      184.04,
      428.61,
      201.82
    ],
    "text": "\u0b9a\u0ba8\u0bcd\u0ba4\u0ba4\u0b95\u0ba8\u0baa\u0bca\u0bcd 38 \u0bb5\u0baf\u0ba4\u0bc1\u0bb2\u0b9f\u0baf \u0bb5\u0ba4\u0bcd\u0ba4\u0bb2\u0bb3 \u0baa\u0b95\u0bc1\u0ba4\u0bbf\u0bb2\u0baf\u0b9a\u0bcd \u0ba4\u0b9a\u0bca\u0bcd\u0ba8\u0bcd\u0ba4\u0bb5\u0bca\u0bcd.",
    "fonts": [
      "Kavivanar-Regular"
    ],
    "sizes": [
      12.0
    ]
  },
  {
    "page_number": 5,
    "bbox": [
      108.02,
      215.72,
      525.66,
      251.41
    ],
    "text": "\u0b95\u0bbf\u0bca\u0bbf\u0baa\u0ba4\u0bcd\u0baa\u0b95\u0bca\u0b9f \u0baa\u0baa\u0bca\u0bb2\u0bbf\u0bb8\u0bca\u0bca\u0bcd \u0ba4\u0bae\u0bb2\u0ba4\u0bbf\u0b95 \u0bb5\u0bbf\u0b9a\u0bca\u0bb0\u0bb2\u0bc8\u0b95\u0bb2\u0bb3 \u0ba4\u0bae\u0bb1\u0bcd\u0baa\u0b95\u0bca\u0bc8\u0bcd\u0b9f\u0bc1 \u0bb5\u0bb0\u0bc1\u0b95\u0bbf\u0ba9\u0bcd\u0bb1\u0ba9\u0bca\u0bcd.",
    "fonts": [
      "Kavivanar-Regular"
    ],
    "sizes": [
      12.0
    ]
  },
  {
    "page_number": 5,
    "bbox": [
      108.02,
      265.43,
      233.2,
      283.21
    ],
    "text": "\u0baa\u0baa\u0bca\u0bb2\u0bbf\u0bb8\u0bcd \u0b8a\u0b9f\u0b95\u0baa\u0bcd \u0baa\u0bbf\u0bca\u0bbf\u0bb5\u0bc1.",
    "fonts": [
      "Kavivanar-Regular"
    ],
    "sizes": [
      12.0
    ]
  },
  {
    "page_number": 5,
    "bbox": [
      107.42,
      297.64,
      506.14,
      346.68
    ],
    "text": "Suspect Arrested with Illegal Liquor \u2013 Walana Central Anti-Corruption Unit",
    "fonts": [
      "TimesNewRomanPS-BoldMT"
    ],
    "sizes": [
      12.0
    ]
  },
  {
    "page_number": 5,
    "bbox": [
      107.42,
      363.28,
      521.45,
      431.78
    ],
    "text": "On the morning of 09.06.2026, officers attached to the Walana Central Anti-Corruption Unit carried out a raid in the Nahena area within the Kiribathgoda Police Division and arrested a suspect in possession of 76 litres (102 bottles) of illicit liquor. The suspect was subsequently handed over to the Kiribathgoda Police Station for further legal action.",
    "fonts": [
      "TimesNewRomanPSMT"
    ],
    "sizes": [
      12.0
    ]
  },
  {
    "page_number": 5,
    "bbox": [
      107.42,
      446.22,
      343.15,
      459.5
    ],
    "text": "The suspect is a 38-year-old resident of Wattala.",
    "fonts": [
      "TimesNewRomanPSMT"
    ],
    "sizes": [
      12.0
    ]
  },
  {
    "page_number": 5,
    "bbox": [
      107.42,
      474.06,
      450.1,
      487.34
    ],
    "text": "Further investigations are being conducted by the Kiribathgoda Police.",
    "fonts": [
      "TimesNewRomanPSMT"
    ],
    "sizes": [
      12.0
    ]
  },
  {
    "page_number": 5,
    "bbox": [
      107.42,
      501.9,
      221.81,
      515.18
    ],
    "text": "Police Media Division",
    "fonts": [
      "TimesNewRomanPS-BoldMT",
      "TimesNewRomanPSMT"
    ],
    "sizes": [
      12.0
    ]
  }
]